tests/__init__.py
tests/test_api_authentication.py
tests/test_auth_service.py
tests/test_game_api.py
tests/test_league_api.py
tests/test_team_api.py
tests/test_user_api.py
yfantasy_api/__init__.py
yfantasy_api/api/__init__.py
yfantasy_api/api/api.py
yfantasy_api/api/auth.py
yfantasy_api/api/game.py
yfantasy_api/api/league.py
yfantasy_api/api/team.py
yfantasy_api/api/terminal.py
yfantasy_api/api/user.py
yfantasy_api/models/__init__.py
yfantasy_api/models/common.py
yfantasy_api/models/game.py
yfantasy_api/models/helpers.py
yfantasy_api/models/league.py
yfantasy_api/models/transaction.py
yfantasy_api/models/user.py
yfantasy_api-0.0.6.dist-info/LICENSE
yfantasy_api-0.0.6.dist-info/METADATA
yfantasy_api-0.0.6.dist-info/WHEEL
yfantasy_api-0.0.6.dist-info/top_level.txt
yfantasy_api-0.0.6.dist-info/RECORD
